{
  "persons": [
    {
      "name": "Ada Lovelace",
      "number": "3644232234662",
      "id": 2
    },
    {
      "name": "Dan Abramov",
      "number": "12-43-234345",
      "id": 3
    },
    {
      "name": "awffaw",
      "number": "4535634",
      "id": 8
    },
    {
      "name": "rtyuuhe5r",
      "number": "6345346",
      "id": 10
    },
    {
      "name": "rthsdertyh",
      "number": "534723457",
      "id": 11
    },
    {
      "name": "",
      "number": "423643",
      "id": 12
    },
    {
      "name": "5647457",
      "number": "thjedrt",
      "id": 13
    }
  ]
}